kep_simgen/__init__.py
kep_simgen/kepware_real_to_simulation.py
kepsimgen-0.0.3.dist-info/METADATA
kepsimgen-0.0.3.dist-info/WHEEL
kepsimgen-0.0.3.dist-info/entry_points.txt
kepsimgen-0.0.3.dist-info/license.txt
kepsimgen-0.0.3.dist-info/top_level.txt
kepsimgen-0.0.3.dist-info/RECORD
